dolmen/__init__.py
dolmen/aeronautics/__init__.py
dolmen/aeronautics/aerodynamics.py
dolmen/aeronautics/gear.py
dolmen/control/LTIsystem.py
dolmen/control/__init__.py
dolmen/control/pid.py
dolmen/electrics/__init__.py
dolmen/electrics/motors.py
dolmen/mechanics/__init__.py
dolmen/mechanics/dynamics.py
dolmen/mechanics/fluidsMechanics.py
dolmen/mechanics/inertia.py
dolmen/mechanics/kinematics.py
dolmen/mechanics/rotational.py
dolmen/utils/PhysicsInt.py
dolmen/utils/PlotTest.py
dolmen/utils/__init__.py
dolmen/utils/cog.py
dolmen/utils/dataTable.py
dolmen/utils/frameworkV10.py
dolmen/utils/frameworkV9.py
dolmen/utils/frameworkV9tmp.py
dolmen/utils/misc.py
dolmen/utils/rho.py
dolmen/utils/volumes.py
dolmensim-2023.7a0.dist-info/LICENSE
dolmensim-2023.7a0.dist-info/METADATA
dolmensim-2023.7a0.dist-info/WHEEL
dolmensim-2023.7a0.dist-info/top_level.txt
dolmensim-2023.7a0.dist-info/RECORD
