Metadata-Version: 2.1
Name: dolmensim
Version: 2023.7a0
Summary: Simulation platform for dynamic systems
Author-email: Nicolas Rouvé <nicolas.rouve@hefr.ch>
Project-URL: Homepage, https://gitlab.forge.hefr.ch/nicolas.rouve/GitDolmen
Classifier: Programming Language :: Python :: 3
Classifier: License :: OSI Approved :: MIT License
Classifier: Operating System :: OS Independent
Requires-Python: >=3.7
License-File: LICENSE
Requires-Dist: numpy
Requires-Dist: pandas
Requires-Dist: matplotlib
